more_pyspark/__init__.py
more_pyspark/more_pyspark.py
more_pyspark-0.1.4.dist-info/WHEEL
more_pyspark-0.1.4.dist-info/METADATA
more_pyspark-0.1.4.dist-info/RECORD
